<annotation>
	<folder>IPC-Picture</folder>
	<filename>156.jpg</filename>
	<path>E:\IPC-Picture\156.jpg</path>
	<source>
		<database>Unknown</database>
	</source>
	<size>
		<width>1920</width>
		<height>1080</height>
		<depth>3</depth>
	</size>
	<segmented>0</segmented>
	<object>
		<name>person</name>
		<pose>Unspecified</pose>
		<truncated>0</truncated>
		<difficult>0</difficult>
		<bndbox>
			<xmin>497</xmin>
			<ymin>610</ymin>
			<xmax>605</xmax>
			<ymax>732</ymax>
		</bndbox>
	</object>
	<object>
		<name>person</name>
		<pose>Unspecified</pose>
		<truncated>0</truncated>
		<difficult>0</difficult>
		<bndbox>
			<xmin>593</xmin>
			<ymin>596</ymin>
			<xmax>671</xmax>
			<ymax>714</ymax>
		</bndbox>
	</object>
	<object>
		<name>person</name>
		<pose>Unspecified</pose>
		<truncated>0</truncated>
		<difficult>0</difficult>
		<bndbox>
			<xmin>517</xmin>
			<ymin>358</ymin>
			<xmax>579</xmax>
			<ymax>524</ymax>
		</bndbox>
	</object>
	<object>
		<name>person</name>
		<pose>Unspecified</pose>
		<truncated>0</truncated>
		<difficult>0</difficult>
		<bndbox>
			<xmin>785</xmin>
			<ymin>334</ymin>
			<xmax>843</xmax>
			<ymax>478</ymax>
		</bndbox>
	</object>
	<object>
		<name>person</name>
		<pose>Unspecified</pose>
		<truncated>0</truncated>
		<difficult>0</difficult>
		<bndbox>
			<xmin>775</xmin>
			<ymin>246</ymin>
			<xmax>819</xmax>
			<ymax>376</ymax>
		</bndbox>
	</object>
	<object>
		<name>person</name>
		<pose>Unspecified</pose>
		<truncated>0</truncated>
		<difficult>0</difficult>
		<bndbox>
			<xmin>903</xmin>
			<ymin>284</ymin>
			<xmax>957</xmax>
			<ymax>420</ymax>
		</bndbox>
	</object>
	<object>
		<name>person</name>
		<pose>Unspecified</pose>
		<truncated>0</truncated>
		<difficult>0</difficult>
		<bndbox>
			<xmin>821</xmin>
			<ymin>144</ymin>
			<xmax>857</xmax>
			<ymax>234</ymax>
		</bndbox>
	</object>
	<object>
		<name>person</name>
		<pose>Unspecified</pose>
		<truncated>0</truncated>
		<difficult>0</difficult>
		<bndbox>
			<xmin>1091</xmin>
			<ymin>150</ymin>
			<xmax>1125</xmax>
			<ymax>242</ymax>
		</bndbox>
	</object>
	<object>
		<name>person</name>
		<pose>Unspecified</pose>
		<truncated>0</truncated>
		<difficult>0</difficult>
		<bndbox>
			<xmin>1015</xmin>
			<ymin>62</ymin>
			<xmax>1043</xmax>
			<ymax>148</ymax>
		</bndbox>
	</object>
	<object>
		<name>person</name>
		<pose>Unspecified</pose>
		<truncated>0</truncated>
		<difficult>0</difficult>
		<bndbox>
			<xmin>1107</xmin>
			<ymin>66</ymin>
			<xmax>1145</xmax>
			<ymax>150</ymax>
		</bndbox>
	</object>
</annotation>
